unistrant/__init__.py
unistrant/__main__.py
unistrant/app.py
unistrant/command.py
unistrant/error.py
unistrant/http.py
unistrant/options.py
unistrant/record.py
unistrant/sams.py
unistrant/settings.py
unistrant-0.1a8.dist-info/METADATA
unistrant-0.1a8.dist-info/WHEEL
unistrant-0.1a8.dist-info/entry_points.txt
unistrant-0.1a8.dist-info/top_level.txt
unistrant-0.1a8.dist-info/RECORD
