Metadata-Version: 2.4
Name: unistrant
Version: 0.1a8
Summary: A unified client for the SAMS Accounting and Metrics System
Requires-Python: >=3.12
Requires-Dist: requests
